wrgl/__init__.py
wrgl/coldiff.py
wrgl/coldiff_test.py
wrgl/commit.py
wrgl/config.py
wrgl/diff.py
wrgl/diffreader.py
wrgl/isoformat.py
wrgl/isoformat_test.py
wrgl/repository.py
wrgl/repository_test.py
wrgl/serialize.py
wrgl/serialize_test.py
wrgl/tar.py
wrgl/uma.py
wrgl/vcr_test.py
wrgl-0.13.4.dist-info/LICENSE
wrgl-0.13.4.dist-info/METADATA
wrgl-0.13.4.dist-info/WHEEL
wrgl-0.13.4.dist-info/top_level.txt
wrgl-0.13.4.dist-info/RECORD
