Metadata-Version: 2.1
Name: wrgl
Version: 0.13.4
Summary: Data matching utilities
Home-page: https://github.com/wrgl/python-sdk
Author: Khoi Pham
Author-email: pckhoi@gmail.com
Project-URL: Bug Tracker, https://github.com/wrgl/python-sdk/issues
Classifier: Programming Language :: Python :: 3
Classifier: License :: OSI Approved :: Apache Software License
Classifier: Operating System :: OS Independent
Requires-Python: >=3.7
License-File: LICENSE
Requires-Dist: requests (>=2.26.0)
Requires-Dist: requests-toolbelt (>=0.9.1)
Requires-Dist: attrs (>=21.2.0)
